Index/__init__.py
Index/index.py
indexyz-0.1.7.dist-info/licenses/LICENSE
indexyz-0.1.7.dist-info/METADATA
indexyz-0.1.7.dist-info/WHEEL
indexyz-0.1.7.dist-info/top_level.txt
indexyz-0.1.7.dist-info/RECORD
