Metadata-Version: 2.4
Name: indexyz
Version: 0.1.7
Summary: Biblioteca para interactuar con Google Sheets.
Author: Palomino Ramos Yony Leonardo
Author-email: yony.palomino.r@uni.pe
License: MIT
Classifier: Programming Language :: Python :: 3
Classifier: License :: OSI Approved :: MIT License
Classifier: Operating System :: OS Independent
Requires-Python: >=3.11.8
License-File: LICENSE
Requires-Dist: google-auth==2.38.0
Requires-Dist: google-api-python-client==2.162.0
Requires-Dist: google-auth-httplib2==0.2.0
Requires-Dist: customtkinter==5.2.2
Dynamic: author
Dynamic: author-email
Dynamic: classifier
Dynamic: description
Dynamic: description-content-type
Dynamic: license
Dynamic: license-file
Dynamic: requires-dist
Dynamic: requires-python
Dynamic: summary
